CHANGELOG.md
MANIFEST.in
README.md
requirements.txt
setup.py
buildutils/__init__.py
buildutils/__init__.pyc
buildutils/build.py
buildutils/build.pyc
buildutils/bundle.py
buildutils/bundle.pyc
buildutils/config.py
buildutils/config.pyc
buildutils/constants.py
buildutils/detect.py
buildutils/detect.pyc
buildutils/misc.py
buildutils/misc.pyc
buildutils/msg.py
buildutils/msg.pyc
buildutils/patch.py
buildutils/patch.pyc
buildutils/setup_travis.sh
buildutils/vers.cpp
capnp/__init__.pxd
capnp/__init__.py
capnp/_gen.py
capnp/c++.capnp
capnp/schema.capnp
capnp/version.py
capnp/helpers/__init__.pxd
capnp/helpers/asyncHelper.h
capnp/helpers/capabilityHelper.h
capnp/helpers/checkCompiler.h
capnp/helpers/fixMaybe.h
capnp/helpers/helpers.pxd
capnp/helpers/non_circular.pxd
capnp/helpers/rpcHelper.h
capnp/helpers/serialize.h
capnp/includes/__init__.pxd
capnp/includes/capnp_cpp.pxd
capnp/includes/schema_cpp.pxd
capnp/includes/types.pxd
capnp/lib/__init__.pxd
capnp/lib/__init__.py
capnp/lib/capnp.cpp
capnp/lib/capnp.pxd
capnp/lib/capnp.pyx
capnp/lib/pickle_helper.py
capnp/templates/module.pyx
capnp/templates/setup.py.tmpl
pycapnp_for_marv.egg-info/PKG-INFO
pycapnp_for_marv.egg-info/SOURCES.txt
pycapnp_for_marv.egg-info/dependency_links.txt
pycapnp_for_marv.egg-info/entry_points.txt
pycapnp_for_marv.egg-info/requires.txt
pycapnp_for_marv.egg-info/top_level.txt
test/test_capability.py
test/test_capability_context.py
test/test_capability_old.py
test/test_large_read.py
test/test_load.py
test/test_object.py
test/test_regression.py
test/test_response.py
test/test_rpc.py
test/test_rpc_calculator.py
test/test_schema.py
test/test_serialization.py
test/test_struct.py
test/test_threads.py